pyiotown/__init__.py
pyiotown/command.py
pyiotown/delete.py
pyiotown/get.py
pyiotown/post.py
pyiotown/post_process.py
pyiotown-0.6.4.dist-info/LICENSE
pyiotown-0.6.4.dist-info/METADATA
pyiotown-0.6.4.dist-info/WHEEL
pyiotown-0.6.4.dist-info/entry_points.txt
pyiotown-0.6.4.dist-info/pbr.json
pyiotown-0.6.4.dist-info/top_level.txt
pyiotown-0.6.4.dist-info/RECORD
