Metadata-Version: 2.1
Name: pyiotown
Version: 0.6.4
Summary: IOTOWN Library
Home-page: https://github.com/CoXlabInc/pyiotow
Author: CoXlab Inc.
Author-email: support@coxlab.kr
Maintainer: Jongsoo Jeong
Maintainer-email: jsjeong@coxlab.k
License: MIT
Project-URL: Bug Tracker, https://github.com/CoXlabInc/pyiotown/issues
Keywords: iotown,iot,lora
Classifier: License :: OSI Approved :: MIT License
Classifier: Operating System :: OS Independent
Classifier: Programming Language :: Python :: 3
License-File: LICENSE
Requires-Dist: pbr
Requires-Dist: setuptools
Requires-Dist: wheel
Requires-Dist: requests
Requires-Dist: paho-mqtt>=2.0.0
Requires-Dist: asyncio
Requires-Dist: aiohttp
